__init__.py
setup.py
fetcher/__init__.py
fetcher/fetcher.py
fetcher.egg-info/PKG-INFO
fetcher.egg-info/SOURCES.txt
fetcher.egg-info/dependency_links.txt
fetcher.egg-info/requires.txt
fetcher.egg-info/top_level.txt
nchecker/__init__.py
nchecker/config.py
nchecker/nchecker.py
nchecker/nx.db
tests/__init__.py
tests/fetcher_tests.py
tests/lazyio_tests.py
tests/upload_tests.py
tests/webpyserver.py