Metadata-Version: 1.0
Name: fetcher
Version: 0.9.2.6
Summary: simple python fetcher, support head, get, post action, file upload, etc
Home-page: http://code.taobao.org/trac/fetcher
Author: Mutang(牧唐)
Author-email: xlty.0512@gmail.com
License: New BSD License
Keywords: python fetcher spider charset
Platform: UNKNOWN
